<?xml version="1.0" encoding="UTF-8"?>
<!-- Japanese -->
<language>
   <page id="8888888" voice="no">
      <!-- JP_TradeSubscriptionExplorer -->
      <!-- ~~~~~~~~~~~~~~~~~~~~~~~~~ -->
      <t id="1931">ワーフ?</t>
      <t id="1932">造船所?</t>
      <t id="1933">装備ドック?</t>
      <t id="1934">取引ステーション?</t>
      <t id="1935">海賊基地?</t>
      <t id="1936">スクラップ処理施設?</t>
      <t id="1937">防衛ステーション?</t>
      <t id="1938">派閥本部?</t>
      <t id="1939">特別ではないステーション?</t>
      <!-- ~~~~~~~~~~~~~~~~~~~~~~~~~ -->
      <t id="1941">取引サブスクリプションの更新</t>
      <!-- ~~~~~~~~~~~~~~~~~~~~~~~~~ -->
      <t id="1960">このスクリプトは、あなたの船が特定のセクターのステーションの取引サブスクリプションを自動的に更新することを可能にします。</t>
      <t id="1961">このスクリプトは、あなたの船が全銀河のステーションの取引サブスクリプションを自動的に更新することを可能にします。</t>
      <!-- ~~~~~~~~~~~~~~~~~~~~~~~~~ -->
      <t id="1980">アイドルタイム</t>
      <t id="1981">アイドル: 移動先?</t>
      <t id="1982">どこに移動する?</t>
      <t id="1983">アイドル: フォローする?</t>
      <t id="1984">誰をフォローする?</t>
      <t id="1985">アイドル: ドッキング?</t>
      <t id="1986">ステーションを見つける?</t>
      <t id="1987">どこにドックする?</t>
      <!-- ~~~~~~~~~~~~~~~~~~~~~~~~~ -->
      <t id="1991">オーダータグを追加?</t>
      <!-- ~~~~~~~~~~~~~~~~~~~~~~~~~ -->
      <t id="1993">オーダー設定を保存?</t>
      <t id="1994">オーダー設定をリセット?</t>
      <t id="1995">オーダー設定を保存しました。</t>
      <t id="1996">オーダー設定をリセットしました。</t>
      <!-- ~~~~~~~~~~~~~~~~~~~~~~~~~ -->
      <t id="1997">\033#B600CCCC#</t>
      <t id="1998">\033#FF00CC66#</t>
      <t id="1999">\033X</t>
      <!-- ~~~~~~~~~~~~~~~~~~~~~~~~~ -->
   </page>
</language>