<?xml version="1.0" encoding="UTF-8"?>
<!-- Russian ~~ Русский -->
<language>
   <page id="8888888" voice="no">
      <!-- ~~~~~~~~~~~~~~~~~~~~~~~~~ -->
      <!-- JP_AbandonedShipExplorer -->
      <!-- ~~~~~~~~~~~~~~~~~~~~~~~~~ -->
      <t id="100">Режим ASE</t>
      <t id="101">Заполнять навигационные маяки?</t>
      <t id="102">Лимит пополнения</t>
      <!-- ~~~~~~~~~~~~~~~~~~~~~~~~~ -->
      <t id="120">Заброшенный корабль</t>
      <t id="121">Я прибыл к заброшенному кораблю:</t>
      <t id="122">Я жду вас, пока вы не перехватите управление заброшенным кораблем.</t>
      <t id="123">Я жду вас, пока вы не перехватите управление заброшенным кораблем и не вернетесь на борт моего.</t>
      <t id="124">Я отметил заброшенный корабль и продолжаю с следующим.</t>
      <t id="125">Я отправил морпеха на заброшенный корабль и жду, пока он не перехватит его управление.</t>
      <t id="126">Для обеспечения безопасности наш только что завоеванный корабль теперь отправится к станции для стыковки.</t>
      <!-- ~~~~~~~~~~~~~~~~~~~~~~~~~ -->
      <t id="140">Перейти к заброшенному кораблю</t>
      <t id="141">Отметить заброшенный корабль</t>
      <t id="142">Зайти на борт заброшенного корабля</t>
      <!-- ~~~~~~~~~~~~~~~~~~~~~~~~~ -->
      <t id="150">Нет или недостаточно навигационных маяков, и автоматическое пополнение навигационных маяков отключено.</t>
      <t id="151">Нет морпехов для автоматического захвата корабля.</t>
      <t id="152">Мы не нашли никаких заброшенных кораблей, которые мы могли бы достичь или которые нужно было бы отметить или забрать.</t>
      <!-- ~~~~~~~~~~~~~~~~~~~~~~~~~ -->
      <t id="161">Этот сценарий позволяет вашему космическому кораблю находить, помечать или бортить заброшенные корабли по всей галактике.</t>
      <!-- ~~~~~~~~~~~~~~~~~~~~~~~~~ -->
   </page>
</language>