<?xml version="1.0" encoding="UTF-8"?>
<!-- Portuguese (Brazil) ~~ Português (Brasil) -->

<language>
   <page id="8888888" voice="no">
      <!-- ~~~~~~~~~~~~~~~~~~~~~~~~~ -->
      <!-- JP_CollectPlaceables -->
      <!-- ~~~~~~~~~~~~~~~~~~~~~~~~~ -->
      <t id="800">Coletar minas regulares?</t>
      <t id="801">Coletar minas rastreadoras?</t>
      <t id="802">Coletar minas amigo/inimigo?</t>
      <t id="803">Coletar torres laser Mk1?</t>
      <t id="804">Coletar torres laser Mk2?</t>
      <t id="805">Coletar satélites regulares?</t>
      <t id="806">Coletar satélites avançados?</t>
      <t id="807">Coletar balizas de navegação?</t>
      <t id="808">Coletar sondas de recursos?</t>
      <!-- ~~~~~~~~~~~~~~~~~~~~~~~~~ -->
      <t id="810">Vender itens colocáveis?</t>
      <t id="811">Vender minas regulares?</t>
      <t id="812">Vender minas rastreadoras?</t>
      <t id="813">Vender minas amigo/inimigo?</t>
      <t id="814">Vender torres laser Mk1?</t>
      <t id="815">Vender torres laser Mk2?</t>
      <t id="816">Vender satélites regulares?</t>
      <t id="817">Vender satélites avançados?</t>
      <t id="818">Vender balizas de navegação?</t>
      <t id="819">Vender sondas de recursos?</t>
      <!-- ~~~~~~~~~~~~~~~~~~~~~~~~~ -->
      <t id="840">Coletar itens colocáveis</t>
      <t id="841">Vender itens colocáveis</t>
      <!-- ~~~~~~~~~~~~~~~~~~~~~~~~~ -->
      <t id="860">\033#FFe27100#Coleta Pausada\033X</t>
      <t id="861">Vou proceder à venda dos objetos de localização, que valem:\n%1.</t>
      <t id="862">Não há mais espaço de armazenamento disponível para coletar objetos de localização adicionais, e não tenho permissão para esvaziar meu armazenamento implantável.</t>
      <t id="863">O armazenamento para objetos de localização está cheio, e não nos é permitido vender os objetos de localização que temos atualmente.</t>
      <t id="864">Não há mais objetos de localização restantes dentro do meu espaço de trabalho definido que precisamos coletar.</t>
      <t id="865">Vou mudar para o modo ocioso e tentar novamente mais tarde.</t>
      <t id="866">Vou começar a coletar objetos de localização no setor %2%1\033X.</t>
      <t id="867">Coletado: %1\nSetor: %3%2\033X</t>
      <!-- ~~~~~~~~~~~~~~~~~~~~~~~~~ -->
      <t id="870">Coleta itens colocáveis, como satélites ou minas, em um único setor.</t>
      <t id="871">Coleta itens colocáveis, como satélites ou minas, em toda a galáxia.</t>
      <!-- ~~~~~~~~~~~~~~~~~~~~~~~~~ -->
   </page>
</language>